LICENSE
MANIFEST.in
README.md
setup.py
clicol/__init__.py
clicol/clicol.py
clicol/command.py
clicol/plugins.py
clicol.egg-info/PKG-INFO
clicol.egg-info/SOURCES.txt
clicol.egg-info/dependency_links.txt
clicol.egg-info/entry_points.txt
clicol.egg-info/not-zip-safe
clicol.egg-info/requires.txt
clicol.egg-info/top_level.txt
clicol/builtinplugins/__init__.py
clicol/builtinplugins/humannumbers.py
clicol/ini/cm_cisco.ini
clicol/ini/cm_common.ini
clicol/ini/cm_juniper.ini
clicol/ini/colors_putty.ini
clicol/ini/colors_securecrt.ini
clicol/ini/ct_dbg_net.ini
clicol/ini/ct_lbg_net.ini
doc/bashrc
doc/clicol.cfg
doc/clicol_customcmap.ini
doc/clicol_customcolors.ini
doc/clicol_customct.ini
doc/plugins.cfg
tests/__init__.py
tests/checkct.py
tests/debug-clicol.py
tests/listcolors.py